km3db/__init__.py
km3db/core.py
km3db/extras.py
km3db/logger.py
km3db/tools.py
km3db/version.py
km3db/cli/detx.py
km3db/cli/km3db.py
km3db/cli/km3dbcookie.py
km3db/cli/runinfo.py
km3db/cli/runtable.py
km3db/cli/streamds.py
km3db/cli/wtd.py
km3db-0.15.0.dist-info/licenses/LICENSE
km3db-0.15.0.dist-info/METADATA
km3db-0.15.0.dist-info/WHEEL
km3db-0.15.0.dist-info/entry_points.txt
km3db-0.15.0.dist-info/top_level.txt
km3db-0.15.0.dist-info/RECORD
