Metadata-Version: 2.4
Name: km3db
Version: 0.15.0
Summary: KM3NeT Database Library
Author-email: Tamas Gal <tamas.gal@fau.de>
Maintainer-email: Tamas Gal <tamas.gal@fau.de>
Project-URL: Homepage, https://git.km3net.de/km3py/km3db
Project-URL: Documentation, https://km3py.pages.km3net.de/km3db/
Project-URL: Repository, https://git.km3net.de/km3py/km3db.git
Project-URL: Issues, https://git.km3net.de/km3py/km3db/-/issues
Project-URL: Changelog, https://km3py.pages.km3net.de/km3db/changelog.html
Classifier: Development Status :: 5 - Production/Stable
Classifier: Intended Audience :: Developers
Classifier: Intended Audience :: Science/Research
Classifier: License :: OSI Approved :: MIT License
Classifier: Operating System :: OS Independent
Classifier: Programming Language :: Python
Classifier: Programming Language :: Python :: 3
Classifier: Programming Language :: Python :: 3 :: Only
Classifier: Programming Language :: Python :: 3.8
Classifier: Programming Language :: Python :: 3.9
Classifier: Programming Language :: Python :: 3.10
Classifier: Programming Language :: Python :: 3.11
Classifier: Programming Language :: Python :: 3.12
Classifier: Topic :: Scientific/Engineering
Requires-Python: >=3.8
License-File: LICENSE
Requires-Dist: docopt
Requires-Dist: pytz
Requires-Dist: requests
Requires-Dist: setuptools_scm
Requires-Dist: numpy
Provides-Extra: dev
Requires-Dist: black; extra == "dev"
Requires-Dist: km3net_testdata>=0.2.7; extra == "dev"
Requires-Dist: matplotlib; extra == "dev"
Requires-Dist: pandas; extra == "dev"
Requires-Dist: memory_profiler; extra == "dev"
Requires-Dist: mock; extra == "dev"
Requires-Dist: numpydoc; extra == "dev"
Requires-Dist: pytest; extra == "dev"
Requires-Dist: pytest-cov; extra == "dev"
Requires-Dist: pytest-watch; extra == "dev"
Requires-Dist: sphinx; extra == "dev"
Requires-Dist: sphinx-autoapi; extra == "dev"
Requires-Dist: sphinx-gallery>=0.1.12; extra == "dev"
Requires-Dist: sphinx_rtd_theme; extra == "dev"
Requires-Dist: sphinxcontrib-versioning; extra == "dev"
Requires-Dist: wheel; extra == "dev"
Provides-Extra: extras
Requires-Dist: pandas; extra == "extras"
Requires-Dist: h5py; extra == "extras"
Dynamic: license-file
